guadalupe_weather/__init__.py
guadalupe_weather/cli.py
guadalupe_weather/get_daily_mean.py
guadalupe_weather/get_outliers.py
guadalupe_weather/get_weather_data.py
guadalupe_weather/plot_weather_variables.py
guadalupe_weather-0.2.2.dist-info/entry_points.txt
guadalupe_weather-0.2.2.dist-info/licenses/LICENSE
guadalupe_weather-0.2.2.dist-info/WHEEL
guadalupe_weather-0.2.2.dist-info/METADATA
guadalupe_weather-0.2.2.dist-info/RECORD
