Metadata-Version: 2.4
Name: guadalupe_weather
Version: 0.2.2
Summary: Paquete analisis de clima en Isla Guadalupe
Home-page: https://bitbucket.org/IslasGECI/clima_guadalupe/
Author: Ciencia de Datos • GECI
Author-email: ciencia.datos@islas.org.mx
Requires-Python: >=3.9
Classifier: License :: OSI Approved :: GNU General Public License v3 or later (GPLv3+)
License-File: LICENSE
Requires-Dist: geci_plots
Requires-Dist: matplotlib
Requires-Dist: pandas
Requires-Dist: typer[all]
Requires-Dist: matplotlib-stubs ; extra == "dev"
Requires-Dist: pandas-stubs ; extra == "dev"
Requires-Dist: types-click ; extra == "dev"
Provides-Extra: dev
